Metadata-Version: 1.1
Name: remotesingularityspawner
Version: 0.0.3
Summary: RemoteSingularitySpawner: A custom spawner for Jupyterhub in singularity container.
Home-page: https://github.com/fanxinping/remotesingularityspawner
Author: xinping fan
Author-email: 897488736@qq.com
License: BSD
Download-URL: https://github.com/fanxinping/remotesingularityspawner/archive/v0.0.2.tar.gz
Keywords: Interactive,Interpreter,Shell,Web
Platform: Linux
Platform: Mac OS X
Classifier: Intended Audience :: Developers
Classifier: Intended Audience :: System Administrators
Classifier: Intended Audience :: Science/Research
Classifier: License :: OSI Approved :: BSD License
Classifier: Programming Language :: Python
Classifier: Programming Language :: Python :: 3
